cribo-0.8.2.data/scripts/cribo
cribo-0.8.2.dist-info/METADATA
cribo-0.8.2.dist-info/WHEEL
cribo-0.8.2.dist-info/licenses/LICENSE
cribo/__init__.py
cribo/__main__.py
cribo/py.typed
cribo-0.8.2.dist-info/RECORD
