Metadata-Version: 2.4
Name: cribo
Version: 0.8.2
Classifier: Development Status :: 3 - Alpha
Classifier: Intended Audience :: Developers
Classifier: License :: OSI Approved :: MIT License
Classifier: Programming Language :: Python :: 3
Classifier: Programming Language :: Python :: 3.10
Classifier: Programming Language :: Python :: 3.11
Classifier: Programming Language :: Python :: 3.12
Classifier: Programming Language :: Rust
Classifier: Topic :: Software Development :: Build Tools
Classifier: Topic :: Software Development :: Libraries :: Python Modules
License-File: LICENSE
Summary: Python source bundler that produces a single .py file from multi-module projects
Keywords: bundler,python,deployment,pyspark,lambda
Author-email: Konstantin Vyatkin <tino@vtkn.io>
Requires-Python: >=3.8
Project-URL: Homepage, https://github.com/ophidiarium/cribo
Project-URL: Repository, https://github.com/ophidiarium/cribo
Project-URL: Documentation, https://github.com/ophidiarium/cribo#readme
Project-URL: Issues, https://github.com/ophidiarium/cribo/issues
